agentv2/__init__.py
agentv2/prompts/Agent.md
agentv2/prompts/FinalReply.md
agentv2/prompts/Todo.md
agentv2/prompts/TodoRewrite.md
agentv2/schemas/AgentMemory.py
agentv2/schemas/AgentState.py
agentv2/schemas/SessionMemory.py
agentv2/schemas/TodoSchema.py
agentv2/schemas/__init__.py
agentv2/src/__init__.py
agentv2/src/agent.py
agentv2/src/executor.py
agentv2/src/planner.py
agentv2/src/session_store.py
agentv2/utils/Prompts.py
agentv2/utils/__init__.py
agentv2/utils/llm.py
agentv2/utils/logger.py
agentv2/utils/validators.py
agentv2-0.1.4.dist-info/METADATA
agentv2-0.1.4.dist-info/WHEEL
agentv2-0.1.4.dist-info/RECORD
