Metadata-Version: 2.4
Name: agentv2
Version: 0.1.4
Summary: A production-ready Python framework for building autonomous AI agents that can plan, validate, and execute complex tasks using LLMs and custom tools
Author-email: "Ch.Varun" <varun30ec4@gmail.com>
License: MIT
Keywords: agent,ai,autonomous,llm,task-execution
Classifier: Development Status :: 4 - Beta
Classifier: Intended Audience :: Developers
Classifier: License :: OSI Approved :: MIT License
Classifier: Programming Language :: Python :: 3
Classifier: Programming Language :: Python :: 3.12
Classifier: Programming Language :: Python :: 3.13
Requires-Python: >=3.12
Requires-Dist: build>=1.4.0
Requires-Dist: ddgs>=9.10.0
Requires-Dist: hatchling>=1.28.0
Requires-Dist: litellm>=1.80.16
Requires-Dist: pydantic>=2.0.0
Requires-Dist: python-dotenv>=1.0.0
Requires-Dist: rich>=14.2.0
Requires-Dist: twine>=6.2.0
Provides-Extra: dev
Requires-Dist: black>=25.12.0; extra == 'dev'
Requires-Dist: isort>=7.0.0; extra == 'dev'
Requires-Dist: pytest-cov>=4.0.0; extra == 'dev'
Requires-Dist: pytest>=8.0.0; extra == 'dev'
Requires-Dist: ruff>=0.14.11; extra == 'dev'
